prelude_sdk_beta/__init__.py
prelude_sdk_beta/controllers/__init__.py
prelude_sdk_beta/controllers/build_controller.py
prelude_sdk_beta/controllers/detect_controller.py
prelude_sdk_beta/controllers/export_controller.py
prelude_sdk_beta/controllers/generate_controller.py
prelude_sdk_beta/controllers/http_controller.py
prelude_sdk_beta/controllers/iam_controller.py
prelude_sdk_beta/controllers/jobs_controller.py
prelude_sdk_beta/controllers/partner_controller.py
prelude_sdk_beta/controllers/probe_controller.py
prelude_sdk_beta/controllers/scm_controller.py
prelude_sdk_beta/models/__init__.py
prelude_sdk_beta/models/account.py
prelude_sdk_beta/models/codes.py
prelude_sdk_beta-1467.dist-info/licenses/LICENSE
prelude_sdk_beta-1467.dist-info/METADATA
prelude_sdk_beta-1467.dist-info/WHEEL
prelude_sdk_beta-1467.dist-info/top_level.txt
prelude_sdk_beta-1467.dist-info/RECORD
